{
  "address": {
    "street_address": "221B Baker Street",
    "city": "London",
    "state": "Great Britain"
  },
  "organization": {
    "name": "Tracim",
    "roles": [
      "developer",
      "administrator"
    ]
  },
  "first_name": "Sherlock",
  "last_name": "Holmes",
  "phone_number": "9999999999",
  "birthday_date": "1854-12-15",
  "bio": "Sherlock Holmes is a fictional private detective created by British author Sir Arthur Conan Doyle. Referring to himself as a \"consulting detective\" in the stories, Holmes is known for his proficiency with observation, deduction, forensic science, and logical reasoning that borders on the fantastic, which he employs when investigating cases for a wide variety of clients, including Scotland Yard. "
}
