{
  "This content is archived": "Este conteúdo está arquivado",
  "Restore": "Restaurar",
  "This content is deleted": "Este conteúdo está eliminado",
  "This content is deprecated": "Este conteúdo está obsoleto",
  "You have a pending draft": "Você tem um rascunho pendente",
  "resume writing": "continuar a escrever",
  "latest version :": "última versão:",
  "Form generator": "Gerador de formulário",
  "Generate a Form": "Gerar um formulário",
  "A content with same name already exists": "Um conteúdo com o mesmo nome já existe",
  "Error while saving new title": "Erro ao guardar novo título",
  "Error while saving new version": "Erro ao guardar nova versão",
  "Error while saving new comment": "Erro ao guardar novo comentário",
  "Error while changing status": "Erro ao mudar de status",
  "Error while archiving document": "Erro ao arquivar o documento",
  "Error while deleting document": "Erro ao deletar o documento",
  "Error while restoring document": "Erro ao restaurar o documento",
  "Edit": "Editar",
  "Last version": "Última versão",
  "A content with the same name already exists": "Um conteúdo com o mesmo nome já existe",
  "Error while creating document": "Erro ao criar o documento",
  "New form": "Novo formulário",
  "Validate and create": "Validar e criar",
  "Document's title": "Título do documento",
  "Cancel": "Cancelar",
  "Validate": "Validar",
  "Title undefined": "Título indeterminado"
}
